axi_read_base.v
module axi_m_read #(
	parameter integer	MAX_BURST_LEN	=	256,
	parameter integer	ADDR_WIDTH		=	32,
	parameter integer	DATA_WIDTH		=	32,

	parameter integer	ID_WIDTH		=	1,
	parameter integer	AUSER_WIDTH		=	1,
	parameter integer	USER_WIDTH		=	1
) (
	// Control Signals
	input						i_ren,
	input	[ADDR_WIDTH-1:0]	i_start_address,
	input	[31:0]				i_read_size,
	output						o_rdone,

	input						i_fixed_burst,

	// FIFO Interface
	input						i_fifo_full,
	output	[DATA_WIDTH-1:0]	o_fifo_data,
	output						o_fifo_en,

	// AXI-Full
	// Global Clock Signal.
	input						M_ACLK,
	// Global Reset Singal. This Signal is Active Low
	input						M_ARESETN,

	// - Address
	output	[ID_WIDTH-1:0]		M_ARID,
	output	[ADDR_WIDTH-1:0]	M_ARADDR,
	output	[7:0]				M_ARLEN,
	output	[2:0]				M_ARSIZE,
	output	[1:0]				M_ARBURST,
	output						M_ARLOCK,
	output	[3:0]				M_ARCACHE,
	output	[2:0]				M_ARPROT,
	output	[3:0]				M_ARQOS,
	output	[AUSER_WIDTH-1:0]	M_ARUSER,
	output						M_ARVALID,
	input						M_ARREADY,
	// - Data
	input	[ID_WIDTH-1:0]		M_RID,
	input	[DATA_WIDTH-1:0]	M_RDATA,
	input	[1:0]				M_RRESP,
	input						M_RLAST,
	input	[USER_WIDTH-1:0]	M_RUSER,
	input						M_RVALID,
	output						M_RREADY
);
	function integer clogb2 (input integer bit_depth); 
	begin 
		for(clogb2=0; bit_depth>0; clogb2=clogb2+1) 
			bit_depth = bit_depth >> 1; 
	end 
	endfunction 

	// Read State list
	parameter	[2:0]	IDLE			=	3'b000, 
						INIT_READ		=	3'b001,
						READ_DATA		=	3'b010,
						READ_DATA_END	=	3'b011,
						READ_END		=	3'b100,
						GAP				=	3'b101;

	localparam integer	TNUM			=	clogb2(MAX_BURST_LEN-1);

	reg		[2:0]				r_rstate;		// read state register
	reg		[31:0]				r_total_size;	// total read data size
	reg		[31:0]				r_rem_size;		// data counter

	reg							r_reads_done;

	reg		[7:0]				r_burst_count;	// data counter
	reg							r_burst_addr;
	reg							r_burst_busy;

	reg							r_arvalid;
	reg							r_rready;

	reg 	[ADDR_WIDTH-1 : 0] 	r_araddr;

	wire						rnext = M_RVALID && r_rready;

	//Read Address (AR)
	assign M_ARID			=	'b0;
	assign M_ARADDR			=	r_araddr;
	//Burst length
	assign M_ARLEN			=	(r_rem_size > MAX_BURST_LEN*(DATA_WIDTH/8)) ? MAX_BURST_LEN-1 : ((r_rem_size/(DATA_WIDTH/8))-1);
	//Size should be C_M_AXI_DATA_WIDTH, in 2^n bytes, otherwise narrow bursts are used
	assign M_ARSIZE			=	clogb2((DATA_WIDTH/8)-1);
	//INCR burst type 00:Fixed, 01:Increment
	assign M_ARBURST		=	(i_fixed_burst) ? 2'b00 : 2'b01;

	//Read address request valid Response
	assign M_ARVALID		=	r_arvalid;
	//Read and Read Response
	assign M_RREADY			=	r_rready;

	assign M_RRESP			=	2'b00;	// OKAY

	// Unused
	assign M_RUSER		= 'b0;
	assign M_ARUSER		= 'b0;
	assign M_ARLOCK		= 1'b0;
	assign M_ARCACHE	= 4'b0010;
	assign M_ARPROT		= 3'h0;
	assign M_ARQOS		= 4'h0;

	// Main State Machine
	always @(posedge M_ACLK) begin
		if ( M_ARESETN == 0 ) begin
			r_rstate		<=	IDLE;
			r_burst_addr	<=	1'b0;
			r_total_size	<=	32'b0;
			r_rem_size		<=	32'b0;
		end else begin
			case (r_rstate)
				IDLE: begin				// 待機状態: 読み出し要求待ち
					if (i_ren) begin
						r_total_size	<=	i_read_size;
						r_rem_size		<=	i_read_size;
						r_rstate		<=	INIT_READ;
						r_burst_addr	<=	1'b0;
					end else begin
						r_rstate	<=	IDLE;
					end
				end
				INIT_READ: begin		// 読み出しアドレス発行
					r_rstate	<=	READ_DATA;
				end
				READ_DATA: begin
					if (r_reads_done) begin
						r_rstate	<=	READ_DATA_END;
					end else begin
						r_rstate	<=	READ_DATA;
						if (~r_arvalid && ~r_burst_addr && ~r_burst_busy) begin
							r_burst_addr	<=	1'b1;
						end else if (r_arvalid && M_ARREADY) begin
							r_burst_addr	<=	1'b0;
						end
					end
				end
				READ_DATA_END: begin	// 読み出しデータ量の判定
					if (MAX_BURST_LEN == 0) begin
						if (r_rem_size <= DATA_WIDTH/8) begin	
							r_rstate	<=	READ_END;
							r_rem_size	<=	0;
						end else begin
							r_rstate	<=	INIT_READ;
							r_rem_size	<=	r_rem_size - DATA_WIDTH/8;
						end
					end else begin
						if (r_rem_size <= MAX_BURST_LEN*(DATA_WIDTH/8)) begin	
							r_rstate	<=	READ_END;
							r_rem_size	<=	0;
						end else begin
							r_rstate	<=	INIT_READ;
							r_rem_size	<=	r_rem_size - MAX_BURST_LEN*(DATA_WIDTH/8);
						end
					end 
				end
				READ_END: begin
					if(~i_ren)
						r_rstate	<=	GAP;
				end
				GAP: begin
					r_rstate	<=	IDLE;
				end
				default: begin
					r_rstate	<=	IDLE;
				end
			endcase
		end
	end

	assign	o_rdone = (r_rstate == READ_END);

	// Read Address Channel
	always @(posedge M_ACLK) begin 
		if ( M_ARESETN == 0 ) begin
			r_arvalid <= 1'b0;
		end else if ( ~r_arvalid && r_burst_addr && ~r_rready ) begin
			r_arvalid <= 1'b1;
		end else if ( M_ARREADY && r_arvalid ) begin
			r_arvalid <= 1'b0;
		end else begin
			r_arvalid <= r_arvalid;
		end
	end
	

	// Read Address Generation 
	generate//: Read_address_gen
		if (MAX_BURST_LEN == 0) begin
			always @(posedge M_ACLK) begin
				if ( M_ARESETN == 0 ) begin
					r_araddr	<=	32'b0;
				end else if (r_rstate == IDLE) begin
					if (i_ren)
						r_araddr	<=	i_start_address;
				end else if (M_ARREADY && r_arvalid) begin
					if (i_fixed_burst)
						r_araddr	<=	r_araddr;
					else 
						r_araddr	<=	r_araddr + DATA_WIDTH/8;
				end else begin
					r_araddr 	<=	r_araddr;
				end
			end
		end else begin
			always @(posedge M_ACLK) begin
				if ( M_ARESETN == 0 ) begin
					r_araddr	<=	32'b0;
				end else if (r_rstate == IDLE) begin
					if (i_ren)
						r_araddr	<=	i_start_address;
				end else if (M_ARREADY && r_arvalid) begin
					if (M_ARBURST == 2'b00)
						r_araddr	<=	r_araddr;
					else if (M_ARBURST == 2'b01)
						r_araddr	<=	r_araddr + MAX_BURST_LEN*(DATA_WIDTH/8);
				end else begin
					r_araddr <= r_araddr;
				end
			end
		end
	endgenerate 
	
	// Burst Size Calc
	generate//: Read_burst_size_calc
		if (MAX_BURST_LEN != 0) begin
			always @(posedge M_ACLK) begin
				if ( M_ARESETN == 1'b0 || r_rstate == READ_END) begin
					r_burst_count	<=	0;
				end else begin
					if (rnext) begin
						r_burst_count	<=	r_burst_count + 1;
					end else begin
						r_burst_count	<=	r_burst_count;
					end
				end
			end
		end
	endgenerate

	// Read Transaction
	generate//: Read_ready
		if (MAX_BURST_LEN == 0) begin
			always @(posedge M_ACLK) begin	// burst busy flag
				if (M_ARESETN == 0) begin
					r_burst_busy <= 1'b0;                                                                            
				end else if (r_burst_addr) begin
					r_burst_busy <= 1'b1;
				end else if (rnext) begin
					r_burst_busy <= 0;
				end
			end

			always @(posedge M_ACLK) begin
				if (M_ARESETN == 0 ) begin
					r_rready <= 1'b0;
				end else if (M_RVALID || M_ARREADY && M_ARVALID) begin
					if (r_rready) begin
						r_rready <= 1'b0;
					end else begin
						r_rready <= !i_fifo_full;
					end
				end
			end
		end else begin
			always @(posedge M_ACLK) begin	// burst busy flag
				if (M_ARESETN == 0) begin
					r_burst_busy <= 1'b0;                                                                            
				end else if (r_burst_addr) begin
					r_burst_busy <= 1'b1;
				end else if (rnext && M_RLAST) begin
					r_burst_busy <= 0;
				end
			end

			always @(posedge M_ACLK) begin		// read ready signal
				if (M_ARESETN == 0 ) begin
					r_rready <= 1'b0;
				end else if (M_RVALID) begin
					if (r_rready && M_RLAST) begin
						r_rready <= 1'b0;
					end else begin
						r_rready <= !i_fifo_full;
					end
				end
			end
		end
	endgenerate

	// Read Done Flag
	generate
		if (MAX_BURST_LEN == 0) begin
			always @(posedge M_ACLK) begin	// burst read done flag
				if (M_ARESETN == 0) begin
					r_reads_done	<=	1'b0;
				end else if (r_rstate == READ_DATA_END ||
								r_rstate == READ_END) begin
					r_reads_done	<=	1'b0;
				end else if (rnext) begin
					r_reads_done	<=	1'b1;
				end else begin
					r_reads_done	<=	r_reads_done;
				end
			end
		end else begin
			always @(posedge M_ACLK) begin	// burst read done flag
				if (M_ARESETN == 0) begin
					r_reads_done	<=	1'b0;
				end else if (r_rstate == READ_DATA_END ||
								r_rstate == READ_END) begin
					r_reads_done	<=	1'b0;
				end else if (rnext && M_RLAST) begin
					r_reads_done	<=	1'b1;
				end else begin
					r_reads_done	<=	r_reads_done;
				end
			end
		end
	endgenerate

	// Read Data Write to FIFO
	assign	o_fifo_data = M_RDATA;
	assign	o_fifo_en = rnext;
	
endmodule

tb/tb_read.v
// axi master read testbench wrapper
`timescale 1ns / 1ps

module tb_axi_mr (
	// Control Signals
	input						i_ren,
	input	[31:0]				i_start_address,
	input	[31:0]				i_read_size,
	output						o_rdone,

	input						i_fixed_burst,

	// AXI-Full
	// Global Clock Signal.
	input						M_ACLK,
	// Global Reset Singal. This Signal is Active Low
	input						M_ARESETN,

	// Write
	// - Address
	output						M_AXI_AWID,
	output	[31:0]				M_AXI_AWADDR,
	output	[7:0]				M_AXI_AWLEN,
	output	[2:0]				M_AXI_AWSIZE,
	output	[1:0]				M_AXI_AWBURST,
	output						M_AXI_AWLOCK,
	output	[3:0]				M_AXI_AWCACHE,
	output	[2:0]				M_AXI_AWQOS,
	output						M_AXI_AWUSER,
	output	[2:0]				M_AXI_AWPROT,
	output						M_AXI_AWVALID,
	input						M_AXI_AWREADY,
	// - Data
	output	[31:0]				M_AXI_WDATA,
	output	[3:0]				M_AXI_WSTRB,
	output						M_AXI_WLAST,
	output						M_AXI_WUSER,
	output						M_AXI_WVALID,
	input						M_AXI_WREADY,
	// - Response
	input						M_AXI_BID,
	input	[1:0]				M_AXI_BRESP,
	input						M_AXI_BUSER,
	input						M_AXI_BVALID,
	output						M_AXI_BREADY,

	// Read
	// - Address
	output						M_AXI_ARID,
	output	[31:0]				M_AXI_ARADDR,
	output	[7:0]				M_AXI_ARLEN,
	output	[2:0]				M_AXI_ARSIZE,
	output	[1:0]				M_AXI_ARBURST,
	output						M_AXI_ARLOCK,
	output	[3:0]				M_AXI_ARCACHE,
	output	[2:0]				M_AXI_ARPROT,
	output	[3:0]				M_AXI_ARQOS,
	output						M_AXI_ARUSER,
	output						M_AXI_ARVALID,
	input						M_AXI_ARREADY,
	// - Data
	input						M_AXI_RID,
	input	[31:0]				M_AXI_RDATA,
	input	[1:0]				M_AXI_RRESP,
	input						M_AXI_RLAST,
	input						M_AXI_RUSER,
	input						M_AXI_RVALID,
	output						M_AXI_RREADY
);

	axi_m_read #(
		.MAX_BURST_LEN		(256),
		.ADDR_WIDTH			(32),
		.DATA_WIDTH			(32)
	) u_axi_m_read (
		.i_ren				(i_ren),
		.i_start_address	(i_start_address),
		.i_read_size		(i_read_size),
		.o_rdone			(o_rdone),

		.i_fixed_burst		(i_fixed_burst),

		.i_fifo_full		(1'b0),
		//.i_fifo_empty		(),
		//.o_fifo_data		(),
		//.o_fifo_en		(),

		.M_ACLK				(M_ACLK),
		.M_ARESETN			(M_ARESETN),

		.M_ARID				(M_AXI_ARID),
		.M_ARADDR			(M_AXI_ARADDR),
		.M_ARLEN			(M_AXI_ARLEN),
		.M_ARSIZE			(M_AXI_ARSIZE),
		.M_ARBURST			(M_AXI_ARBURST),
		.M_ARLOCK			(M_AXI_ARLOCK),
		.M_ARCACHE			(M_AXI_ARCACHE),
		.M_ARPROT			(M_AXI_ARPROT),
		.M_ARQOS			(M_AXI_ARQOS),
		.M_ARUSER           (M_AXI_ARUSER),
		.M_ARVALID          (M_AXI_ARVALID),
		.M_ARREADY          (M_AXI_ARREADY),

		.M_RID             (M_AXI_RID),
		.M_RDATA           (M_AXI_RDATA),
		.M_RRESP           (M_AXI_RRESP),
		.M_RLAST           (M_AXI_RLAST),
		.M_RUSER           (M_AXI_RUSER),
		.M_RVALID          (M_AXI_RVALID),
		.M_RREADY          (M_AXI_RREADY)
	);

	`ifdef COCOTB_SIM
	initial begin
		$dumpfile ("axi_m_read.vcd");
		$dumpvars (0, tb_axi_mr);
		#1;
	end
	`endif
	
endmodule

tb/sim_build/axi_m_read.vcd
$date
	Sat Nov  1 22:45:18 2025
$end
$version
	Icarus Verilog
$end
$timescale
	1ps
$end
$scope module tb_axi_mr $end
$var wire 1 ! M_ACLK $end
$var wire 1 " M_ARESETN $end
$var wire 4 # M_AXI_ARCACHE [3:0] $end
$var wire 1 $ M_AXI_ARID $end
$var wire 1 % M_AXI_ARLOCK $end
$var wire 3 & M_AXI_ARPROT [2:0] $end
$var wire 4 ' M_AXI_ARQOS [3:0] $end
$var wire 1 ( M_AXI_ARREADY $end
$var wire 1 ) M_AXI_ARUSER $end
$var wire 32 * M_AXI_AWADDR [31:0] $end
$var wire 2 + M_AXI_AWBURST [1:0] $end
$var wire 4 , M_AXI_AWCACHE [3:0] $end
$var wire 1 - M_AXI_AWID $end
$var wire 8 . M_AXI_AWLEN [7:0] $end
$var wire 1 / M_AXI_AWLOCK $end
$var wire 3 0 M_AXI_AWPROT [2:0] $end
$var wire 3 1 M_AXI_AWQOS [2:0] $end
$var wire 1 2 M_AXI_AWREADY $end
$var wire 3 3 M_AXI_AWSIZE [2:0] $end
$var wire 1 4 M_AXI_AWUSER $end
$var wire 1 5 M_AXI_AWVALID $end
$var wire 1 6 M_AXI_BID $end
$var wire 1 7 M_AXI_BREADY $end
$var wire 2 8 M_AXI_BRESP [1:0] $end
$var wire 1 9 M_AXI_BUSER $end
$var wire 1 : M_AXI_BVALID $end
$var wire 32 ; M_AXI_RDATA [31:0] $end
$var wire 1 < M_AXI_RID $end
$var wire 1 = M_AXI_RLAST $end
$var wire 2 > M_AXI_RRESP [1:0] $end
$var wire 1 ? M_AXI_RUSER $end
$var wire 1 @ M_AXI_RVALID $end
$var wire 32 A M_AXI_WDATA [31:0] $end
$var wire 1 B M_AXI_WLAST $end
$var wire 1 C M_AXI_WREADY $end
$var wire 4 D M_AXI_WSTRB [3:0] $end
$var wire 1 E M_AXI_WUSER $end
$var wire 1 F M_AXI_WVALID $end
$var wire 1 G i_fixed_burst $end
$var wire 32 H i_read_size [31:0] $end
$var wire 1 I i_ren $end
$var wire 32 J i_start_address [31:0] $end
$var wire 1 K o_rdone $end
$var wire 1 L M_AXI_RREADY $end
$var wire 1 M M_AXI_ARVALID $end
$var wire 3 N M_AXI_ARSIZE [2:0] $end
$var wire 8 O M_AXI_ARLEN [7:0] $end
$var wire 2 P M_AXI_ARBURST [1:0] $end
$var wire 32 Q M_AXI_ARADDR [31:0] $end
$scope module u_axi_m_read $end
$var wire 1 ! M_ACLK $end
$var wire 32 R M_ARADDR [31:0] $end
$var wire 4 S M_ARCACHE [3:0] $end
$var wire 1 " M_ARESETN $end
$var wire 1 $ M_ARID $end
$var wire 1 % M_ARLOCK $end
$var wire 3 T M_ARPROT [2:0] $end
$var wire 4 U M_ARQOS [3:0] $end
$var wire 1 ( M_ARREADY $end
$var wire 1 ) M_ARUSER $end
$var wire 1 M M_ARVALID $end
$var wire 32 V M_RDATA [31:0] $end
$var wire 1 < M_RID $end
$var wire 1 = M_RLAST $end
$var wire 1 L M_RREADY $end
$var wire 2 W M_RRESP [1:0] $end
$var wire 1 ? M_RUSER $end
$var wire 1 @ M_RVALID $end
$var wire 1 X i_fifo_full $end
$var wire 1 G i_fixed_burst $end
$var wire 32 Y i_read_size [31:0] $end
$var wire 1 I i_ren $end
$var wire 32 Z i_start_address [31:0] $end
$var wire 32 [ o_fifo_data [31:0] $end
$var wire 1 \ o_fifo_en $end
$var wire 1 ] rnext $end
$var wire 1 K o_rdone $end
$var wire 3 ^ M_ARSIZE [2:0] $end
$var wire 8 _ M_ARLEN [7:0] $end
$var wire 2 ` M_ARBURST [1:0] $end
$var parameter 32 a ADDR_WIDTH $end
$var parameter 32 b AUSER_WIDTH $end
$var parameter 32 c DATA_WIDTH $end
$var parameter 3 d GAP $end
$var parameter 3 e IDLE $end
$var parameter 32 f ID_WIDTH $end
$var parameter 3 g INIT_READ $end
$var parameter 32 h MAX_BURST_LEN $end
$var parameter 3 i READ_DATA $end
$var parameter 3 j READ_DATA_END $end
$var parameter 3 k READ_END $end
$var parameter 32 l TNUM $end
$var parameter 32 m USER_WIDTH $end
$var reg 32 n r_araddr [31:0] $end
$var reg 1 o r_arvalid $end
$var reg 1 p r_burst_addr $end
$var reg 1 q r_burst_busy $end
$var reg 8 r r_burst_count [7:0] $end
$var reg 1 s r_reads_done $end
$var reg 32 t r_rem_size [31:0] $end
$var reg 1 u r_rready $end
$var reg 3 v r_rstate [2:0] $end
$var reg 32 w r_total_size [31:0] $end
$scope function clogb2 $end
$var integer 32 x bit_depth [31:0] $end
$upscope $end
$scope begin genblk1 $end
$upscope $end
$scope begin genblk2 $end
$upscope $end
$scope begin genblk3 $end
$upscope $end
$scope begin genblk4 $end
$upscope $end
$upscope $end
$upscope $end
$enddefinitions $end
$comment Show the parameter values. $end
$dumpall
b1 m
b1000 l
b100 k
b11 j
b10 i
b100000000 h
b1 g
b1 f
b0 e
b101 d
b100000 c
b1 b
b100000 a
$end
#0
$dumpvars
b0 x
b0 w
b0 v
0u
b0 t
0s
b0 r
0q
0p
0o
b0 n
b1 `
b11111111 _
b10 ^
0]
0\
bz [
bz Z
bz Y
0X
b0 W
bz V
b0 U
b0 T
b10 S
b0 R
b0 Q
b1 P
b11111111 O
b10 N
0M
0L
0K
bz J
0I
bz H
0G
zF
zE
bz D
zC
zB
bz A
z@
0?
b0 >
z=
z<
bz ;
z:
z9
bz 8
z7
z6
z5
z4
bz 3
z2
bz 1
bz 0
z/
bz .
z-
bz ,
bz +
bz *
0)
z(
b0 '
b0 &
0%
0$
b10 #
0"
1!
$end
#5000
0!
#10000
1!
#15000
0!
#20000
1!
#25000
0!
#30000
1!
#35000
0!
#40000
1!
#45000
0!
#50000
b10010000000 H
b10010000000 Y
b0 J
b0 Z
x=
bx [
bx ;
bx V
x<
0@
0(
x6
0:
0C
02
1!
0"
#55000
0!
#60000
1!
#65000
0!
#70000
1(
1C
12
1!
1"
#75000
0!
#80000
1I
1!
#85000
0!
#90000
b1 v
b10010000000 t
b10010000000 w
1!
#95000
0!
#100000
b10 v
1!
#105000
0!
#110000
1p
1!
#115000
0!
#120000
1q
1M
1o
1!
#125000
0!
#130000
0M
0o
0p
b10000000000 Q
b10000000000 R
b10000000000 n
1!
#135000
0!
#140000
1@
0=
b0 [
b0 ;
b0 V
0<
1!
#145000
0!
#150000
1\
1]
1L
1u
1!
#155000
0!
#160000
b100 [
b100 ;
b100 V
b1 r
1!
#165000
0!
#170000
b1000 [
b1000 ;
b1000 V
b10 r
1!
#175000
0!
#180000
b1100 [
b1100 ;
b1100 V
b11 r
1!
#185000
0!
#190000
b10000 [
b10000 ;
b10000 V
b100 r
1!
#195000
0!
#200000
b10100 [
b10100 ;
b10100 V
b101 r
1!
#205000
0!
#210000
b11000 [
b11000 ;
b11000 V
b110 r
1!
#215000
0!
#220000
b11100 [
b11100 ;
b11100 V
b111 r
1!
#225000
0!
#230000
b100000 [
b100000 ;
b100000 V
b1000 r
1!
#235000
0!
#240000
b100100 [
b100100 ;
b100100 V
b1001 r
1!
#245000
0!
#250000
b101000 [
b101000 ;
b101000 V
b1010 r
1!
#255000
0!
#260000
b101100 [
b101100 ;
b101100 V
b1011 r
1!
#265000
0!
#270000
b110000 [
b110000 ;
b110000 V
b1100 r
1!
#275000
0!
#280000
b110100 [
b110100 ;
b110100 V
b1101 r
1!
#285000
0!
#290000
b111000 [
b111000 ;
b111000 V
b1110 r
1!
#295000
0!
#300000
b111100 [
b111100 ;
b111100 V
b1111 r
1!
#305000
0!
#310000
b1000000 [
b1000000 ;
b1000000 V
b10000 r
1!
#315000
0!
#320000
b1000100 [
b1000100 ;
b1000100 V
b10001 r
1!
#325000
0!
#330000
b1001000 [
b1001000 ;
b1001000 V
b10010 r
1!
#335000
0!
#340000
b1001100 [
b1001100 ;
b1001100 V
b10011 r
1!
#345000
0!
#350000
b1010000 [
b1010000 ;
b1010000 V
b10100 r
1!
#355000
0!
#360000
b1010100 [
b1010100 ;
b1010100 V
b10101 r
1!
#365000
0!
#370000
b1011000 [
b1011000 ;
b1011000 V
b10110 r
1!
#375000
0!
#380000
b1011100 [
b1011100 ;
b1011100 V
b10111 r
1!
#385000
0!
#390000
b1100000 [
b1100000 ;
b1100000 V
b11000 r
1!
#395000
0!
#400000
b1100100 [
b1100100 ;
b1100100 V
b11001 r
1!
#405000
0!
#410000
b1101000 [
b1101000 ;
b1101000 V
b11010 r
1!
#415000
0!
#420000
b1101100 [
b1101100 ;
b1101100 V
b11011 r
1!
#425000
0!
#430000
b1110000 [
b1110000 ;
b1110000 V
b11100 r
1!
#435000
0!
#440000
b1110100 [
b1110100 ;
b1110100 V
b11101 r
1!
#445000
0!
#450000
b1111000 [
b1111000 ;
b1111000 V
b11110 r
1!
#455000
0!
#460000
b1111100 [
b1111100 ;
b1111100 V
b11111 r
1!
#465000
0!
#470000
b10000000 [
b10000000 ;
b10000000 V
b100000 r
1!
#475000
0!
#480000
b10000100 [
b10000100 ;
b10000100 V
b100001 r
1!
#485000
0!
#490000
b10001000 [
b10001000 ;
b10001000 V
b100010 r
1!
#495000
0!
#500000
b10001100 [
b10001100 ;
b10001100 V
b100011 r
1!
#505000
0!
#510000
b10010000 [
b10010000 ;
b10010000 V
b100100 r
1!
#515000
0!
#520000
b10010100 [
b10010100 ;
b10010100 V
b100101 r
1!
#525000
0!
#530000
b10011000 [
b10011000 ;
b10011000 V
b100110 r
1!
#535000
0!
#540000
b10011100 [
b10011100 ;
b10011100 V
b100111 r
1!
#545000
0!
#550000
b10100000 [
b10100000 ;
b10100000 V
b101000 r
1!
#555000
0!
#560000
b10100100 [
b10100100 ;
b10100100 V
b101001 r
1!
#565000
0!
#570000
b10101000 [
b10101000 ;
b10101000 V
b101010 r
1!
#575000
0!
#580000
b10101100 [
b10101100 ;
b10101100 V
b101011 r
1!
#585000
0!
#590000
b10110000 [
b10110000 ;
b10110000 V
b101100 r
1!
#595000
0!
#600000
b10110100 [
b10110100 ;
b10110100 V
b101101 r
1!
#605000
0!
#610000
b10111000 [
b10111000 ;
b10111000 V
b101110 r
1!
#615000
0!
#620000
b10111100 [
b10111100 ;
b10111100 V
b101111 r
1!
#625000
0!
#630000
b11000000 [
b11000000 ;
b11000000 V
b110000 r
1!
#635000
0!
#640000
b11000100 [
b11000100 ;
b11000100 V
b110001 r
1!
#645000
0!
#650000
b11001000 [
b11001000 ;
b11001000 V
b110010 r
1!
#655000
0!
#660000
b11001100 [
b11001100 ;
b11001100 V
b110011 r
1!
#665000
0!
#670000
b11010000 [
b11010000 ;
b11010000 V
b110100 r
1!
#675000
0!
#680000
b11010100 [
b11010100 ;
b11010100 V
b110101 r
1!
#685000
0!
#690000
b11011000 [
b11011000 ;
b11011000 V
b110110 r
1!
#695000
0!
#700000
b11011100 [
b11011100 ;
b11011100 V
b110111 r
1!
#705000
0!
#710000
b11100000 [
b11100000 ;
b11100000 V
b111000 r
1!
#715000
0!
#720000
b11100100 [
b11100100 ;
b11100100 V
b111001 r
1!
#725000
0!
#730000
b11101000 [
b11101000 ;
b11101000 V
b111010 r
1!
#735000
0!
#740000
b11101100 [
b11101100 ;
b11101100 V
b111011 r
1!
#745000
0!
#750000
b11110000 [
b11110000 ;
b11110000 V
b111100 r
1!
#755000
0!
#760000
b11110100 [
b11110100 ;
b11110100 V
b111101 r
1!
#765000
0!
#770000
b11111000 [
b11111000 ;
b11111000 V
b111110 r
1!
#775000
0!
#780000
b11111100 [
b11111100 ;
b11111100 V
b111111 r
1!
#785000
0!
#790000
b100000000 [
b100000000 ;
b100000000 V
b1000000 r
1!
#795000
0!
#800000
b100000100 [
b100000100 ;
b100000100 V
b1000001 r
1!
#805000
0!
#810000
b100001000 [
b100001000 ;
b100001000 V
b1000010 r
1!
#815000
0!
#820000
b100001100 [
b100001100 ;
b100001100 V
b1000011 r
1!
#825000
0!
#830000
b100010000 [
b100010000 ;
b100010000 V
b1000100 r
1!
#835000
0!
#840000
b100010100 [
b100010100 ;
b100010100 V
b1000101 r
1!
#845000
0!
#850000
b100011000 [
b100011000 ;
b100011000 V
b1000110 r
1!
#855000
0!
#860000
b100011100 [
b100011100 ;
b100011100 V
b1000111 r
1!
#865000
0!
#870000
b100100000 [
b100100000 ;
b100100000 V
b1001000 r
1!
#875000
0!
#880000
b100100100 [
b100100100 ;
b100100100 V
b1001001 r
1!
#885000
0!
#890000
b100101000 [
b100101000 ;
b100101000 V
b1001010 r
1!
#895000
0!
#900000
b100101100 [
b100101100 ;
b100101100 V
b1001011 r
1!
#905000
0!
#910000
b100110000 [
b100110000 ;
b100110000 V
b1001100 r
1!
#915000
0!
#920000
b100110100 [
b100110100 ;
b100110100 V
b1001101 r
1!
#925000
0!
#930000
b100111000 [
b100111000 ;
b100111000 V
b1001110 r
1!
#935000
0!
#940000
b100111100 [
b100111100 ;
b100111100 V
b1001111 r
1!
#945000
0!
#950000
b101000000 [
b101000000 ;
b101000000 V
b1010000 r
1!
#955000
0!
#960000
b101000100 [
b101000100 ;
b101000100 V
b1010001 r
1!
#965000
0!
#970000
b101001000 [
b101001000 ;
b101001000 V
b1010010 r
1!
#975000
0!
#980000
b101001100 [
b101001100 ;
b101001100 V
b1010011 r
1!
#985000
0!
#990000
b101010000 [
b101010000 ;
b101010000 V
b1010100 r
1!
#995000
0!
#1000000
b101010100 [
b101010100 ;
b101010100 V
b1010101 r
1!
#1005000
0!
#1010000
b101011000 [
b101011000 ;
b101011000 V
b1010110 r
1!
#1015000
0!
#1020000
b101011100 [
b101011100 ;
b101011100 V
b1010111 r
1!
#1025000
0!
#1030000
b101100000 [
b101100000 ;
b101100000 V
b1011000 r
1!
#1035000
0!
#1040000
b101100100 [
b101100100 ;
b101100100 V
b1011001 r
1!
#1045000
0!
#1050000
b101101000 [
b101101000 ;
b101101000 V
b1011010 r
1!
#1055000
0!
#1060000
b101101100 [
b101101100 ;
b101101100 V
b1011011 r
1!
#1065000
0!
#1070000
b101110000 [
b101110000 ;
b101110000 V
b1011100 r
1!
#1075000
0!
#1080000
b101110100 [
b101110100 ;
b101110100 V
b1011101 r
1!
#1085000
0!
#1090000
b101111000 [
b101111000 ;
b101111000 V
b1011110 r
1!
#1095000
0!
#1100000
b101111100 [
b101111100 ;
b101111100 V
b1011111 r
1!
#1105000
0!
#1110000
b110000000 [
b110000000 ;
b110000000 V
b1100000 r
1!
#1115000
0!
#1120000
b110000100 [
b110000100 ;
b110000100 V
b1100001 r
1!
#1125000
0!
#1130000
b110001000 [
b110001000 ;
b110001000 V
b1100010 r
1!
#1135000
0!
#1140000
b110001100 [
b110001100 ;
b110001100 V
b1100011 r
1!
#1145000
0!
#1150000
b110010000 [
b110010000 ;
b110010000 V
b1100100 r
1!
#1155000
0!
#1160000
b110010100 [
b110010100 ;
b110010100 V
b1100101 r
1!
#1165000
0!
#1170000
b110011000 [
b110011000 ;
b110011000 V
b1100110 r
1!
#1175000
0!
#1180000
b110011100 [
b110011100 ;
b110011100 V
b1100111 r
1!
#1185000
0!
#1190000
b110100000 [
b110100000 ;
b110100000 V
b1101000 r
1!
#1195000
0!
#1200000
b110100100 [
b110100100 ;
b110100100 V
b1101001 r
1!
#1205000
0!
#1210000
b110101000 [
b110101000 ;
b110101000 V
b1101010 r
1!
#1215000
0!
#1220000
b110101100 [
b110101100 ;
b110101100 V
b1101011 r
1!
#1225000
0!
#1230000
b110110000 [
b110110000 ;
b110110000 V
b1101100 r
1!
#1235000
0!
#1240000
b110110100 [
b110110100 ;
b110110100 V
b1101101 r
1!
#1245000
0!
#1250000
b110111000 [
b110111000 ;
b110111000 V
b1101110 r
1!
#1255000
0!
#1260000
b110111100 [
b110111100 ;
b110111100 V
b1101111 r
1!
#1265000
0!
#1270000
b111000000 [
b111000000 ;
b111000000 V
b1110000 r
1!
#1275000
0!
#1280000
b111000100 [
b111000100 ;
b111000100 V
b1110001 r
1!
#1285000
0!
#1290000
b111001000 [
b111001000 ;
b111001000 V
b1110010 r
1!
#1295000
0!
#1300000
b111001100 [
b111001100 ;
b111001100 V
b1110011 r
1!
#1305000
0!
#1310000
b111010000 [
b111010000 ;
b111010000 V
b1110100 r
1!
#1315000
0!
#1320000
b111010100 [
b111010100 ;
b111010100 V
b1110101 r
1!
#1325000
0!
#1330000
b111011000 [
b111011000 ;
b111011000 V
b1110110 r
1!
#1335000
0!
#1340000
b111011100 [
b111011100 ;
b111011100 V
b1110111 r
1!
#1345000
0!
#1350000
b111100000 [
b111100000 ;
b111100000 V
b1111000 r
1!
#1355000
0!
#1360000
b111100100 [
b111100100 ;
b111100100 V
b1111001 r
1!
#1365000
0!
#1370000
b111101000 [
b111101000 ;
b111101000 V
b1111010 r
1!
#1375000
0!
#1380000
b111101100 [
b111101100 ;
b111101100 V
b1111011 r
1!
#1385000
0!
#1390000
b111110000 [
b111110000 ;
b111110000 V
b1111100 r
1!
#1395000
0!
#1400000
b111110100 [
b111110100 ;
b111110100 V
b1111101 r
1!
#1405000
0!
#1410000
b111111000 [
b111111000 ;
b111111000 V
b1111110 r
1!
#1415000
0!
#1420000
b111111100 [
b111111100 ;
b111111100 V
b1111111 r
1!
#1425000
0!
